{
    "@context": [
        "http://iiif.io/api/presentation/2/context.json",
        "http://codh.rois.ac.jp/iiif/curation/1/context.json"
    ],
    "@id": "https://nakamura196.github.io/umesao_yolo3/iiif/curation/X0225912/curation.json",
    "@type": "cr:Curation",
    "label": "Character List",
    "selections": [
        {
            "@id": "https://nakamura196.github.io/umesao_yolo3/iiif/curation/X0225912/range1",
            "@type": "sc:Range",
            "label": "Characters",
            "members": [
                {
                    "@id": "https://umesao.cultural.jp/iiif/item/X0225912/manifest.json/canvas/p1#xywh=99,1216,105,41",
                    "@type": "sc:Canvas",
                    "label": "car",
                    "metadata": [
                        {
                            "label": "Method",
                            "value": "YOLO v3"
                        },
                        {
                            "label": "Score",
                            "value": "0.31629688"
                        },
                        {
                            "label": "Thubmnail Region",
                            "value": "31,380,33,13"
                        }
                    ]
                },
                {
                    "@id": "https://umesao.cultural.jp/iiif/item/X0225912/manifest.json/canvas/p1#xywh=3,1267,140,86",
                    "@type": "sc:Canvas",
                    "label": "car",
                    "metadata": [
                        {
                            "label": "Method",
                            "value": "YOLO v3"
                        },
                        {
                            "label": "Score",
                            "value": "0.881977"
                        },
                        {
                            "label": "Thubmnail Region",
                            "value": "1,396,44,27"
                        }
                    ]
                },
                {
                    "@id": "https://umesao.cultural.jp/iiif/item/X0225912/manifest.json/canvas/p1#xywh=505,1254,278,124",
                    "@type": "sc:Canvas",
                    "label": "car",
                    "metadata": [
                        {
                            "label": "Method",
                            "value": "YOLO v3"
                        },
                        {
                            "label": "Score",
                            "value": "0.9781431"
                        },
                        {
                            "label": "Thubmnail Region",
                            "value": "158,392,87,39"
                        }
                    ]
                },
                {
                    "@id": "https://umesao.cultural.jp/iiif/item/X0225912/manifest.json/canvas/p1#xywh=688,1203,22,60",
                    "@type": "sc:Canvas",
                    "label": "person",
                    "metadata": [
                        {
                            "label": "Method",
                            "value": "YOLO v3"
                        },
                        {
                            "label": "Score",
                            "value": "0.33948898"
                        },
                        {
                            "label": "Thubmnail Region",
                            "value": "215,376,7,19"
                        }
                    ]
                },
                {
                    "@id": "https://umesao.cultural.jp/iiif/item/X0225912/manifest.json/canvas/p1#xywh=371,1299,32,57",
                    "@type": "sc:Canvas",
                    "label": "person",
                    "metadata": [
                        {
                            "label": "Method",
                            "value": "YOLO v3"
                        },
                        {
                            "label": "Score",
                            "value": "0.37325948"
                        },
                        {
                            "label": "Thubmnail Region",
                            "value": "116,406,10,18"
                        }
                    ]
                },
                {
                    "@id": "https://umesao.cultural.jp/iiif/item/X0225912/manifest.json/canvas/p1#xywh=518,1184,28,86",
                    "@type": "sc:Canvas",
                    "label": "person",
                    "metadata": [
                        {
                            "label": "Method",
                            "value": "YOLO v3"
                        },
                        {
                            "label": "Score",
                            "value": "0.48138875"
                        },
                        {
                            "label": "Thubmnail Region",
                            "value": "162,370,9,27"
                        }
                    ]
                },
                {
                    "@id": "https://umesao.cultural.jp/iiif/item/X0225912/manifest.json/canvas/p1#xywh=787,1241,64,137",
                    "@type": "sc:Canvas",
                    "label": "person",
                    "metadata": [
                        {
                            "label": "Method",
                            "value": "YOLO v3"
                        },
                        {
                            "label": "Score",
                            "value": "0.60873467"
                        },
                        {
                            "label": "Thubmnail Region",
                            "value": "246,388,20,43"
                        }
                    ]
                },
                {
                    "@id": "https://umesao.cultural.jp/iiif/item/X0225912/manifest.json/canvas/p1#xywh=928,1235,96,300",
                    "@type": "sc:Canvas",
                    "label": "person",
                    "metadata": [
                        {
                            "label": "Method",
                            "value": "YOLO v3"
                        },
                        {
                            "label": "Score",
                            "value": "0.66270864"
                        },
                        {
                            "label": "Thubmnail Region",
                            "value": "290,386,30,94"
                        }
                    ]
                },
                {
                    "@id": "https://umesao.cultural.jp/iiif/item/X0225912/manifest.json/canvas/p1#xywh=278,1254,38,105",
                    "@type": "sc:Canvas",
                    "label": "person",
                    "metadata": [
                        {
                            "label": "Method",
                            "value": "YOLO v3"
                        },
                        {
                            "label": "Score",
                            "value": "0.76741904"
                        },
                        {
                            "label": "Thubmnail Region",
                            "value": "87,392,12,33"
                        }
                    ]
                },
                {
                    "@id": "https://umesao.cultural.jp/iiif/item/X0225912/manifest.json/canvas/p1#xywh=867,1206,76,240",
                    "@type": "sc:Canvas",
                    "label": "person",
                    "metadata": [
                        {
                            "label": "Method",
                            "value": "YOLO v3"
                        },
                        {
                            "label": "Score",
                            "value": "0.9933172"
                        },
                        {
                            "label": "Thubmnail Region",
                            "value": "271,377,24,75"
                        }
                    ]
                },
                {
                    "@id": "https://umesao.cultural.jp/iiif/item/X0225912/manifest.json/canvas/p1#xywh=99,1216,105,41",
                    "@type": "sc:Canvas",
                    "label": "car",
                    "metadata": [
                        {
                            "label": "Method",
                            "value": "YOLO v3"
                        },
                        {
                            "label": "Score",
                            "value": "0.31629688"
                        },
                        {
                            "label": "Thubmnail Region",
                            "value": "31,380,33,13"
                        }
                    ]
                },
                {
                    "@id": "https://umesao.cultural.jp/iiif/item/X0225912/manifest.json/canvas/p1#xywh=3,1267,140,86",
                    "@type": "sc:Canvas",
                    "label": "car",
                    "metadata": [
                        {
                            "label": "Method",
                            "value": "YOLO v3"
                        },
                        {
                            "label": "Score",
                            "value": "0.881977"
                        },
                        {
                            "label": "Thubmnail Region",
                            "value": "1,396,44,27"
                        }
                    ]
                },
                {
                    "@id": "https://umesao.cultural.jp/iiif/item/X0225912/manifest.json/canvas/p1#xywh=505,1254,278,124",
                    "@type": "sc:Canvas",
                    "label": "car",
                    "metadata": [
                        {
                            "label": "Method",
                            "value": "YOLO v3"
                        },
                        {
                            "label": "Score",
                            "value": "0.9781431"
                        },
                        {
                            "label": "Thubmnail Region",
                            "value": "158,392,87,39"
                        }
                    ]
                },
                {
                    "@id": "https://umesao.cultural.jp/iiif/item/X0225912/manifest.json/canvas/p1#xywh=688,1203,22,60",
                    "@type": "sc:Canvas",
                    "label": "person",
                    "metadata": [
                        {
                            "label": "Method",
                            "value": "YOLO v3"
                        },
                        {
                            "label": "Score",
                            "value": "0.33948898"
                        },
                        {
                            "label": "Thubmnail Region",
                            "value": "215,376,7,19"
                        }
                    ]
                },
                {
                    "@id": "https://umesao.cultural.jp/iiif/item/X0225912/manifest.json/canvas/p1#xywh=371,1299,32,57",
                    "@type": "sc:Canvas",
                    "label": "person",
                    "metadata": [
                        {
                            "label": "Method",
                            "value": "YOLO v3"
                        },
                        {
                            "label": "Score",
                            "value": "0.37325948"
                        },
                        {
                            "label": "Thubmnail Region",
                            "value": "116,406,10,18"
                        }
                    ]
                },
                {
                    "@id": "https://umesao.cultural.jp/iiif/item/X0225912/manifest.json/canvas/p1#xywh=518,1184,28,86",
                    "@type": "sc:Canvas",
                    "label": "person",
                    "metadata": [
                        {
                            "label": "Method",
                            "value": "YOLO v3"
                        },
                        {
                            "label": "Score",
                            "value": "0.48138875"
                        },
                        {
                            "label": "Thubmnail Region",
                            "value": "162,370,9,27"
                        }
                    ]
                },
                {
                    "@id": "https://umesao.cultural.jp/iiif/item/X0225912/manifest.json/canvas/p1#xywh=787,1241,64,137",
                    "@type": "sc:Canvas",
                    "label": "person",
                    "metadata": [
                        {
                            "label": "Method",
                            "value": "YOLO v3"
                        },
                        {
                            "label": "Score",
                            "value": "0.60873467"
                        },
                        {
                            "label": "Thubmnail Region",
                            "value": "246,388,20,43"
                        }
                    ]
                },
                {
                    "@id": "https://umesao.cultural.jp/iiif/item/X0225912/manifest.json/canvas/p1#xywh=928,1235,96,300",
                    "@type": "sc:Canvas",
                    "label": "person",
                    "metadata": [
                        {
                            "label": "Method",
                            "value": "YOLO v3"
                        },
                        {
                            "label": "Score",
                            "value": "0.66270864"
                        },
                        {
                            "label": "Thubmnail Region",
                            "value": "290,386,30,94"
                        }
                    ]
                },
                {
                    "@id": "https://umesao.cultural.jp/iiif/item/X0225912/manifest.json/canvas/p1#xywh=278,1254,38,105",
                    "@type": "sc:Canvas",
                    "label": "person",
                    "metadata": [
                        {
                            "label": "Method",
                            "value": "YOLO v3"
                        },
                        {
                            "label": "Score",
                            "value": "0.76741904"
                        },
                        {
                            "label": "Thubmnail Region",
                            "value": "87,392,12,33"
                        }
                    ]
                },
                {
                    "@id": "https://umesao.cultural.jp/iiif/item/X0225912/manifest.json/canvas/p1#xywh=867,1206,76,240",
                    "@type": "sc:Canvas",
                    "label": "person",
                    "metadata": [
                        {
                            "label": "Method",
                            "value": "YOLO v3"
                        },
                        {
                            "label": "Score",
                            "value": "0.9933172"
                        },
                        {
                            "label": "Thubmnail Region",
                            "value": "271,377,24,75"
                        }
                    ]
                }
            ],
            "within": {
                "@id": "https://umesao.cultural.jp/iiif/item/X0225912/manifest.json",
                "@type": "sc:Manifest",
                "label": "X0225912"
            }
        }
    ]
}