{
    "@context": [
        "http://iiif.io/api/presentation/2/context.json",
        "http://codh.rois.ac.jp/iiif/curation/1/context.json"
    ],
    "@id": "https://nakamura196.github.io/umesao_yolo3/iiif/curation/X0234659/curation.json",
    "@type": "cr:Curation",
    "label": "Character List",
    "selections": [
        {
            "@id": "https://nakamura196.github.io/umesao_yolo3/iiif/curation/X0234659/range1",
            "@type": "sc:Range",
            "label": "Characters",
            "members": [
                {
                    "@id": "https://umesao.cultural.jp/iiif/item/X0234659/manifest.json/canvas/p1#xywh=166,832,119,100",
                    "@type": "sc:Canvas",
                    "label": "bowl",
                    "metadata": [
                        {
                            "label": "Method",
                            "value": "YOLO v3"
                        },
                        {
                            "label": "Score",
                            "value": "0.8759685"
                        },
                        {
                            "label": "Thubmnail Region",
                            "value": "78,390,56,47"
                        }
                    ]
                },
                {
                    "@id": "https://umesao.cultural.jp/iiif/item/X0234659/manifest.json/canvas/p1#xywh=0,878,128,113",
                    "@type": "sc:Canvas",
                    "label": "bowl",
                    "metadata": [
                        {
                            "label": "Method",
                            "value": "YOLO v3"
                        },
                        {
                            "label": "Score",
                            "value": "0.9196458"
                        },
                        {
                            "label": "Thubmnail Region",
                            "value": "0,412,60,53"
                        }
                    ]
                },
                {
                    "@id": "https://umesao.cultural.jp/iiif/item/X0234659/manifest.json/canvas/p1#xywh=930,409,588,603",
                    "@type": "sc:Canvas",
                    "label": "person",
                    "metadata": [
                        {
                            "label": "Method",
                            "value": "YOLO v3"
                        },
                        {
                            "label": "Score",
                            "value": "0.9889599"
                        },
                        {
                            "label": "Thubmnail Region",
                            "value": "436,192,276,283"
                        }
                    ]
                },
                {
                    "@id": "https://umesao.cultural.jp/iiif/item/X0234659/manifest.json/canvas/p1#xywh=341,279,394,712",
                    "@type": "sc:Canvas",
                    "label": "person",
                    "metadata": [
                        {
                            "label": "Method",
                            "value": "YOLO v3"
                        },
                        {
                            "label": "Score",
                            "value": "0.9925902"
                        },
                        {
                            "label": "Thubmnail Region",
                            "value": "160,131,185,334"
                        }
                    ]
                },
                {
                    "@id": "https://umesao.cultural.jp/iiif/item/X0234659/manifest.json/canvas/p1#xywh=697,313,443,695",
                    "@type": "sc:Canvas",
                    "label": "person",
                    "metadata": [
                        {
                            "label": "Method",
                            "value": "YOLO v3"
                        },
                        {
                            "label": "Score",
                            "value": "0.9960418"
                        },
                        {
                            "label": "Thubmnail Region",
                            "value": "327,147,208,326"
                        }
                    ]
                }
            ],
            "within": {
                "@id": "https://umesao.cultural.jp/iiif/item/X0234659/manifest.json",
                "@type": "sc:Manifest",
                "label": "X0234659"
            }
        }
    ]
}