{
    "@context": [
        "http://iiif.io/api/presentation/2/context.json",
        "http://codh.rois.ac.jp/iiif/curation/1/context.json"
    ],
    "@id": "https://nakamura196.github.io/umesao_yolo3/iiif/curation/X0236131/curation.json",
    "@type": "cr:Curation",
    "label": "Character List",
    "selections": [
        {
            "@id": "https://nakamura196.github.io/umesao_yolo3/iiif/curation/X0236131/range1",
            "@type": "sc:Range",
            "label": "Characters",
            "members": [
                {
                    "@id": "https://umesao.cultural.jp/iiif/item/X0236131/manifest.json/canvas/p1#xywh=1139,349,386,315",
                    "@type": "sc:Canvas",
                    "label": "boat",
                    "metadata": [
                        {
                            "label": "Method",
                            "value": "YOLO v3"
                        },
                        {
                            "label": "Score",
                            "value": "0.591793"
                        },
                        {
                            "label": "Thubmnail Region",
                            "value": "534,164,181,148"
                        }
                    ]
                },
                {
                    "@id": "https://umesao.cultural.jp/iiif/item/X0236131/manifest.json/canvas/p1#xywh=473,571,34,36",
                    "@type": "sc:Canvas",
                    "label": "boat",
                    "metadata": [
                        {
                            "label": "Method",
                            "value": "YOLO v3"
                        },
                        {
                            "label": "Score",
                            "value": "0.59715647"
                        },
                        {
                            "label": "Thubmnail Region",
                            "value": "222,268,16,17"
                        }
                    ]
                },
                {
                    "@id": "https://umesao.cultural.jp/iiif/item/X0236131/manifest.json/canvas/p1#xywh=640,535,66,98",
                    "@type": "sc:Canvas",
                    "label": "boat",
                    "metadata": [
                        {
                            "label": "Method",
                            "value": "YOLO v3"
                        },
                        {
                            "label": "Score",
                            "value": "0.6812449"
                        },
                        {
                            "label": "Thubmnail Region",
                            "value": "300,251,31,46"
                        }
                    ]
                },
                {
                    "@id": "https://umesao.cultural.jp/iiif/item/X0236131/manifest.json/canvas/p1#xywh=322,552,104,61",
                    "@type": "sc:Canvas",
                    "label": "boat",
                    "metadata": [
                        {
                            "label": "Method",
                            "value": "YOLO v3"
                        },
                        {
                            "label": "Score",
                            "value": "0.68399334"
                        },
                        {
                            "label": "Thubmnail Region",
                            "value": "151,259,49,29"
                        }
                    ]
                },
                {
                    "@id": "https://umesao.cultural.jp/iiif/item/X0236131/manifest.json/canvas/p1#xywh=727,386,407,307",
                    "@type": "sc:Canvas",
                    "label": "boat",
                    "metadata": [
                        {
                            "label": "Method",
                            "value": "YOLO v3"
                        },
                        {
                            "label": "Score",
                            "value": "0.9455251"
                        },
                        {
                            "label": "Thubmnail Region",
                            "value": "341,181,191,144"
                        }
                    ]
                },
                {
                    "@id": "https://umesao.cultural.jp/iiif/item/X0236131/manifest.json/canvas/p1#xywh=1139,349,386,315",
                    "@type": "sc:Canvas",
                    "label": "boat",
                    "metadata": [
                        {
                            "label": "Method",
                            "value": "YOLO v3"
                        },
                        {
                            "label": "Score",
                            "value": "0.591793"
                        },
                        {
                            "label": "Thubmnail Region",
                            "value": "534,164,181,148"
                        }
                    ]
                },
                {
                    "@id": "https://umesao.cultural.jp/iiif/item/X0236131/manifest.json/canvas/p1#xywh=473,571,34,36",
                    "@type": "sc:Canvas",
                    "label": "boat",
                    "metadata": [
                        {
                            "label": "Method",
                            "value": "YOLO v3"
                        },
                        {
                            "label": "Score",
                            "value": "0.59715647"
                        },
                        {
                            "label": "Thubmnail Region",
                            "value": "222,268,16,17"
                        }
                    ]
                },
                {
                    "@id": "https://umesao.cultural.jp/iiif/item/X0236131/manifest.json/canvas/p1#xywh=640,535,66,98",
                    "@type": "sc:Canvas",
                    "label": "boat",
                    "metadata": [
                        {
                            "label": "Method",
                            "value": "YOLO v3"
                        },
                        {
                            "label": "Score",
                            "value": "0.6812449"
                        },
                        {
                            "label": "Thubmnail Region",
                            "value": "300,251,31,46"
                        }
                    ]
                },
                {
                    "@id": "https://umesao.cultural.jp/iiif/item/X0236131/manifest.json/canvas/p1#xywh=322,552,104,61",
                    "@type": "sc:Canvas",
                    "label": "boat",
                    "metadata": [
                        {
                            "label": "Method",
                            "value": "YOLO v3"
                        },
                        {
                            "label": "Score",
                            "value": "0.68399334"
                        },
                        {
                            "label": "Thubmnail Region",
                            "value": "151,259,49,29"
                        }
                    ]
                },
                {
                    "@id": "https://umesao.cultural.jp/iiif/item/X0236131/manifest.json/canvas/p1#xywh=727,386,407,307",
                    "@type": "sc:Canvas",
                    "label": "boat",
                    "metadata": [
                        {
                            "label": "Method",
                            "value": "YOLO v3"
                        },
                        {
                            "label": "Score",
                            "value": "0.9455251"
                        },
                        {
                            "label": "Thubmnail Region",
                            "value": "341,181,191,144"
                        }
                    ]
                }
            ],
            "within": {
                "@id": "https://umesao.cultural.jp/iiif/item/X0236131/manifest.json",
                "@type": "sc:Manifest",
                "label": "X0236131"
            }
        }
    ]
}